CLASSIFIERS
LICENSE.txt
MANIFEST.in
README.rst
requirements.txt
setup.py
rieapie/__init__.py
rieapie/trickery.py
rieapie/version.py
rieapie.egg-info/PKG-INFO
rieapie.egg-info/SOURCES.txt
rieapie.egg-info/dependency_links.txt
rieapie.egg-info/not-zip-safe
rieapie.egg-info/requires.txt
rieapie.egg-info/top_level.txt
rieapie/wrappers/__init__.py
rieapie/wrappers/twitter.py