Metadata-Version: 1.0
Name: rieapie
Version: 0.0.7.2
Summary: Easy REST api wrapper
Home-page: http://github.com/alisaifee/rieapie
Author: Ali-Akber Saifee
Author-email: ali@indydevs.org
License: Copyright (c) 2013 Ali-Akber Saifee 
